cosmic_ray_pytest/__init__.py
cosmic_ray_pytest/runner.py
cosmic_ray_pytest-1.0.1.dist-info/METADATA
cosmic_ray_pytest-1.0.1.dist-info/RECORD
cosmic_ray_pytest-1.0.1.dist-info/WHEEL
cosmic_ray_pytest-1.0.1.dist-info/entry_points.txt
cosmic_ray_pytest-1.0.1.dist-info/top_level.txt
