Metadata-Version: 2.1
Name: cosmic-ray-pytest
Version: 1.0.1
Summary: Pytest test-runner plugin for Cosmic Ray.
Home-page: https://gitlab.com/pv.zarubin/cosmic_ray_plugins
Author: Sixty North AS
License: MIT License
Platform: UNKNOWN
Requires-Python: >=3.6.0
